rtl/alu.v
module alu #(
    parameter WIDTH = 16
)(
    input  [WIDTH-1:0] A,
    input  [WIDTH-1:0] B,
    input  [3:0] opcode,

    output reg [WIDTH-1:0] result,
    output reg carry_out,
    output reg zero_flag,
    output reg overflow_flag,
    output reg negative_flag
);

reg [WIDTH:0] temp;

always @(*) begin

    result = 0;
    carry_out = 0;
    zero_flag = 0;
    overflow_flag = 0;
    negative_flag = 0;
    temp = 0;

    case (opcode)

        4'b0000: begin
            temp = A + B;
            result = temp[WIDTH-1:0];
            carry_out = temp[WIDTH];
        end

        4'b0001: begin
            temp = A - B;
            result = temp[WIDTH-1:0];
            carry_out = temp[WIDTH];
        end

        4'b0010: begin
            result = A & B;
        end

        4'b0011: begin
            result = A | B;
        end

        4'b0100: begin
            result = A ^ B;
        end

        4'b0101: begin
            result = ~A;
        end

        4'b0110: begin
            result = A << 1;
        end

        4'b0111: begin
            result = A >> 1;
        end

        4'b1000: begin
            result = A * B;
        end

        4'b1001: begin
            result = A + 1;
        end

        4'b1010: begin
            result = A - 1;
        end

        4'b1011: begin
            result = A;
        end

        4'b1100: begin
            result = B;
        end

        4'b1101: begin
            result = ~(A & B);
        end

        4'b1110: begin
            result = ~(A | B);
        end

        4'b1111: begin
            result = ~(A ^ B);
        end

        default: begin
            result = 0;
        end

    endcase

    // Zero Flag
    zero_flag = (result == 0);

    // Negative Flag
    negative_flag = result[WIDTH-1];

    // Overflow Flag
    if (opcode == 4'b0000)
        overflow_flag = (~(A[WIDTH-1] ^ B[WIDTH-1])) &
                        (A[WIDTH-1] ^ result[WIDTH-1]);
    else if (opcode == 4'b0001)
        overflow_flag = (A[WIDTH-1] ^ B[WIDTH-1]) &
                        (A[WIDTH-1] ^ result[WIDTH-1]);

end

endmodule

tb/alu_tb.v
`timescale 1ns/1ps

module alu_tb;

parameter WIDTH = 16;

// Inputs
reg [WIDTH-1:0] A;
reg [WIDTH-1:0] B;
reg [3:0] opcode;

// Outputs
wire [WIDTH-1:0] result;
wire carry_out;
wire zero_flag;
wire overflow_flag;
wire negative_flag;

// Design Under Test (DUT)
alu #(
    .WIDTH(WIDTH)
) dut (
    .A(A),
    .B(B),
    .opcode(opcode),
    .result(result),
    .carry_out(carry_out),
    .zero_flag(zero_flag),
    .overflow_flag(overflow_flag),
    .negative_flag(negative_flag)
);

// Expected values
reg [WIDTH-1:0] expected_result;
reg expected_carry_out;
reg expected_zero_flag;
reg expected_overflow_flag;
reg expected_negative_flag;

integer pass_count;
integer fail_count;

integer i;
    reg [WIDTH:0] expected_temp;

initial begin
    $dumpfile("waveforms/alu.vcd");
    $dumpvars(0, alu_tb);

    pass_count = 0;
    fail_count = 0;
end

task check_result;

    input [WIDTH-1:0] exp_result;
    input exp_carry;
    input exp_zero;
    input exp_overflow;
    input exp_negative;

begin

    #1;

    if ((result == exp_result) &&
        (carry_out == exp_carry) &&
        (zero_flag == exp_zero) &&
        (overflow_flag == exp_overflow) &&
        (negative_flag == exp_negative))
    begin
        pass_count = pass_count + 1;
        $display("PASS");
    end
    else
    begin
        fail_count = fail_count + 1;

        $display("--------------------------------");
        $display("FAIL");
        $display("Expected Result = %h, Actual Result = %h", exp_result, result);
        $display("Expected Carry = %b, Actual Carry = %b", exp_carry, carry_out);
        $display("Expected Zero = %b, Actual Zero = %b", exp_zero, zero_flag);
        $display("Expected Overflow = %b, Actual Overflow = %b", exp_overflow, overflow_flag);
        $display("Expected Negative = %b, Actual Negative = %b", exp_negative, negative_flag);
        $display("--------------------------------");
    end

end

endtask

initial begin

    //-------------------------------------------------
    // Test 1 : ADD
    //-------------------------------------------------
    A = 16'd25;
    B = 16'd10;
    opcode = 4'b0000;

    check_result(16'd35, 1'b0, 1'b0, 1'b0, 1'b0);

    //-------------------------------------------------
    // Test 2 : SUB
    //-------------------------------------------------
    A = 16'd20;
    B = 16'd5;
    opcode = 4'b0001;

    check_result(16'd15, 1'b0, 1'b0, 1'b0, 1'b0);

    //-------------------------------------------------
    // Test 3 : AND
    //-------------------------------------------------
    A = 16'h00FF;
    B = 16'h0F0F;
    opcode = 4'b0010;

    check_result(16'h000F, 1'b0, 1'b0, 1'b0, 1'b0);

    //-------------------------------------------------
    // Test 4 : OR
    //-------------------------------------------------
    A = 16'h00F0;
    B = 16'h0F00;
    opcode = 4'b0011;

    check_result(16'h0FF0, 1'b0, 1'b0, 1'b0, 1'b0);

    //-------------------------------------------------
    // Test 5 : XOR
    //-------------------------------------------------
    A = 16'hAAAA;
    B = 16'h5555;
    opcode = 4'b0100;

    check_result(16'hFFFF, 1'b0, 1'b0, 1'b0, 1'b1);

    //-------------------------------------------------
    // Test 6 : NOT
    //-------------------------------------------------
    A = 16'h00FF;
    opcode = 4'b0101;

    check_result(16'hFF00, 1'b0, 1'b0, 1'b0, 1'b1);

    //-------------------------------------------------
    // Test 7 : Shift Left
    //-------------------------------------------------
    A = 16'h0003;
    opcode = 4'b0110;

    check_result(16'h0006, 1'b0, 1'b0, 1'b0, 1'b0);

    //-------------------------------------------------
    // Test 8 : Shift Right
    //-------------------------------------------------
    A = 16'h0008;
    opcode = 4'b0111;

    check_result(16'h0004, 1'b0, 1'b0, 1'b0, 1'b0);

    //-------------------------------------------------
    // Test 9 : Multiply
    //-------------------------------------------------
    A = 16'd10;
    B = 16'd5;
    opcode = 4'b1000;

    check_result(16'd50, 1'b0, 1'b0, 1'b0, 1'b0);

    //-------------------------------------------------
    // Test 10 : Increment
    //-------------------------------------------------
    A = 16'd99;
    opcode = 4'b1001;

    check_result(16'd100, 1'b0, 1'b0, 1'b0, 1'b0);

    //-------------------------------------------------
    // Test 11 : Decrement
    //-------------------------------------------------
    A = 16'd100;
    opcode = 4'b1010;

    check_result(16'd99, 1'b0, 1'b0, 1'b0, 1'b0);

    //-------------------------------------------------
    // Test 12 : Pass A
    //-------------------------------------------------
    A = 16'h1234;
    opcode = 4'b1011;

    check_result(16'h1234, 1'b0, 1'b0, 1'b0, 1'b0);

    //-------------------------------------------------
    // Test 13 : Pass B
    //-------------------------------------------------
    B = 16'h5678;
    opcode = 4'b1100;

    check_result(16'h5678, 1'b0, 1'b0, 1'b0, 1'b0);

    //-------------------------------------------------
    // Test 14 : NAND
    //-------------------------------------------------
    A = 16'hFFFF;
    B = 16'h0F0F;
    opcode = 4'b1101;

    check_result(16'hF0F0, 1'b0, 1'b0, 1'b0, 1'b1);

    //-------------------------------------------------
    // Test 15 : NOR
    //-------------------------------------------------
    A = 16'h0000;
    B = 16'h0000;
    opcode = 4'b1110;

    check_result(16'hFFFF, 1'b0, 1'b0, 1'b0, 1'b1);

    //-------------------------------------------------
    // Test 16 : XNOR
    //-------------------------------------------------
    A = 16'hAAAA;
    B = 16'h5555;
    opcode = 4'b1111;

    check_result(16'h0000, 1'b0, 1'b1, 1'b0, 1'b0);

    //-------------------------------------------------
    // Corner 1 : Add Zero
    //-------------------------------------------------
    A=16'h0000; B=16'h0000; opcode=4'b0000;
    check_result(16'h0000,0,1,0,0);

    //-------------------------------------------------
    // Corner 2 : Add Carry
    //-------------------------------------------------
    A=16'hFFFF; B=16'h0001; opcode=4'b0000;
    check_result(16'h0000,1,1,0,0);

    //-------------------------------------------------
    // Corner 3 : Add Signed Overflow
    //-------------------------------------------------
    A=16'h7FFF; B=16'h0001; opcode=4'b0000;
    check_result(16'h8000,0,0,1,1);

    //-------------------------------------------------
    // Corner 4 : Add Negative Overflow
    //-------------------------------------------------
    A=16'h8000; B=16'h8000; opcode=4'b0000;
    check_result(16'h0000,1,1,1,0);

    //-------------------------------------------------
    // Corner 5 : Sub Zero
    //-------------------------------------------------
    A=16'd100; B=16'd100; opcode=4'b0001;
    check_result(16'h0000,0,1,0,0);

    //-------------------------------------------------
    // Corner 6 : Sub Negative
    //-------------------------------------------------
    A=16'd5; B=16'd10; opcode=4'b0001;
    check_result(16'hFFFB,1,0,0,1);

    //-------------------------------------------------
    // Corner 7 : Sub Overflow
    //-------------------------------------------------
    A=16'h8000; B=16'h0001; opcode=4'b0001;
    check_result(16'h7FFF,0,0,1,0);

    //-------------------------------------------------
    // Corner 8 : AND All Ones
    //-------------------------------------------------
    A=16'hFFFF; B=16'hFFFF; opcode=4'b0010;
    check_result(16'hFFFF,0,0,0,1);

    //-------------------------------------------------
    // Corner 9 : AND Zero
    //-------------------------------------------------
    A=16'h0000; B=16'hFFFF; opcode=4'b0010;
    check_result(16'h0000,0,1,0,0);

    //-------------------------------------------------
    // Corner 10 : OR Zero
    //-------------------------------------------------
    A=16'h0000; B=16'h0000; opcode=4'b0011;
    check_result(16'h0000,0,1,0,0);

    //-------------------------------------------------
    // Corner 11 : XOR Same
    //-------------------------------------------------
    A=16'hAAAA; B=16'hAAAA; opcode=4'b0100;
    check_result(16'h0000,0,1,0,0);

    //-------------------------------------------------
    // Corner 12 : NOT Zero
    //-------------------------------------------------
    A=16'h0000; opcode=4'b0101;
    check_result(16'hFFFF,0,0,0,1);

    //-------------------------------------------------
    // Corner 13 : Shift Left MSB
    //-------------------------------------------------
    A=16'h8000; opcode=4'b0110;
    check_result(16'h0000,0,1,0,0);

    //-------------------------------------------------
    // Corner 14 : Shift Right One
    //-------------------------------------------------
    A=16'h0001; opcode=4'b0111;
    check_result(16'h0000,0,1,0,0);

    //-------------------------------------------------
    // Corner 15 : Multiply Zero
    //-------------------------------------------------
    A=16'd500; B=16'd0; opcode=4'b1000;
    check_result(16'd0,0,1,0,0);

    //-------------------------------------------------
    // Corner 16 : Multiply One
    //-------------------------------------------------
    A=16'd1234; B=16'd1; opcode=4'b1000;
    check_result(16'd1234,0,0,0,0);

    //-------------------------------------------------
    // Corner 17 : Increment Max
    //-------------------------------------------------
    A=16'hFFFF; opcode=4'b1001;
    check_result(16'h0000,0,1,0,0);

    //-------------------------------------------------
    // Corner 18 : Increment Overflow
    //-------------------------------------------------
    A=16'h7FFF; opcode=4'b1001;
    check_result(16'h8000,0,0,0,1);

    //-------------------------------------------------
    // Corner 19 : Decrement Zero
    //-------------------------------------------------
    A=16'h0000; opcode=4'b1010;
    check_result(16'hFFFF,0,0,0,1);

    //-------------------------------------------------
    // Corner 20 : Pass A
    //-------------------------------------------------
    A=16'hABCD; opcode=4'b1011;
    check_result(16'hABCD,0,0,0,1);

    //-------------------------------------------------
    // Corner 21 : Pass B
    //-------------------------------------------------
    B=16'h1234; opcode=4'b1100;
    check_result(16'h1234,0,0,0,0);

    //-------------------------------------------------
    // Corner 22 : NAND
    //-------------------------------------------------
    A=16'hFFFF; B=16'hFFFF; opcode=4'b1101;
    check_result(16'h0000,0,1,0,0);

    //-------------------------------------------------
    // Corner 23 : NOR
    //-------------------------------------------------
    A=16'h0000; B=16'h0000; opcode=4'b1110;
    check_result(16'hFFFF,0,0,0,1);

    //-------------------------------------------------
    // Corner 24 : XNOR
    //-------------------------------------------------
    A=16'hAAAA; B=16'hAAAA; opcode=4'b1111;
    check_result(16'hFFFF,0,0,0,1);

    //-------------------------------------------------
    // Randomized Testing
    //-------------------------------------------------

    

    for(i = 0; i < 100; i = i + 1)
    begin

        A = $random;
        B = $random;
        opcode = $random % 16;

        case(opcode)

            4'b0000: begin
                expected_temp = A + B;
                expected_result = expected_temp[WIDTH-1:0];
                expected_carry_out = expected_temp[WIDTH];
                expected_overflow_flag =
                    (~(A[WIDTH-1]^B[WIDTH-1])) &
                    (A[WIDTH-1]^expected_result[WIDTH-1]);
            end

            4'b0001: begin
                expected_temp = A - B;
                expected_result = expected_temp[WIDTH-1:0];
                expected_carry_out = expected_temp[WIDTH];
                expected_overflow_flag =
                    (A[WIDTH-1]^B[WIDTH-1]) &
                    (A[WIDTH-1]^expected_result[WIDTH-1]);
            end

            4'b0010: expected_result = A & B;
            4'b0011: expected_result = A | B;
            4'b0100: expected_result = A ^ B;
            4'b0101: expected_result = ~A;
            4'b0110: expected_result = A << 1;
            4'b0111: expected_result = A >> 1;
            4'b1000: expected_result = A * B;
            4'b1001: expected_result = A + 1;
            4'b1010: expected_result = A - 1;
            4'b1011: expected_result = A;
            4'b1100: expected_result = B;
            4'b1101: expected_result = ~(A & B);
            4'b1110: expected_result = ~(A | B);
            4'b1111: expected_result = ~(A ^ B);

        endcase

        if(opcode != 4'b0000 && opcode != 4'b0001)
        begin
            expected_carry_out = 0;
            expected_overflow_flag = 0;
        end

        expected_zero_flag = (expected_result == 0);
        expected_negative_flag = expected_result[WIDTH-1];

        check_result(
            expected_result,
            expected_carry_out,
            expected_zero_flag,
            expected_overflow_flag,
            expected_negative_flag
        );

    end


    //-------------------------------------------------
    // Summary
    //-------------------------------------------------

    $display("=================================");
    $display("PASS = %0d", pass_count);
    $display("FAIL = %0d", fail_count);
    $display("=================================");

    $finish;

end


endmodule

waveforms/alu.vcd
$date
	Sun Jun 28 16:33:04 2026
$end
$version
	Icarus Verilog
$end
$timescale
	1ps
$end
$scope module alu_tb $end
$var wire 1 ! zero_flag $end
$var wire 16 " result [15:0] $end
$var wire 1 # overflow_flag $end
$var wire 1 $ negative_flag $end
$var wire 1 % carry_out $end
$var parameter 32 & WIDTH $end
$var reg 16 ' A [15:0] $end
$var reg 16 ( B [15:0] $end
$var reg 1 ) expected_carry_out $end
$var reg 1 * expected_negative_flag $end
$var reg 1 + expected_overflow_flag $end
$var reg 16 , expected_result [15:0] $end
$var reg 17 - expected_temp [16:0] $end
$var reg 1 . expected_zero_flag $end
$var reg 4 / opcode [3:0] $end
$var integer 32 0 fail_count [31:0] $end
$var integer 32 1 i [31:0] $end
$var integer 32 2 pass_count [31:0] $end
$scope module dut $end
$var wire 16 3 A [15:0] $end
$var wire 16 4 B [15:0] $end
$var wire 4 5 opcode [3:0] $end
$var parameter 32 6 WIDTH $end
$var reg 1 % carry_out $end
$var reg 1 $ negative_flag $end
$var reg 1 # overflow_flag $end
$var reg 16 7 result [15:0] $end
$var reg 17 8 temp [16:0] $end
$var reg 1 ! zero_flag $end
$upscope $end
$scope task check_result $end
$var reg 1 9 exp_carry $end
$var reg 1 : exp_negative $end
$var reg 1 ; exp_overflow $end
$var reg 16 < exp_result [15:0] $end
$var reg 1 = exp_zero $end
$upscope $end
$upscope $end
$enddefinitions $end
$comment Show the parameter values. $end
$dumpall
b10000 6
b10000 &
$end
#0
$dumpvars
0=
b100011 <
0;
0:
09
b100011 8
b100011 7
b0 5
b1010 4
b11001 3
b0 2
bx 1
b0 0
b0 /
x.
bx -
bx ,
x+
x*
x)
b1010 (
b11001 '
0%
0$
0#
b100011 "
0!
$end
#1000
b1111 8
b1111 "
b1111 7
b1111 <
b1 /
b1 5
b101 (
b101 4
b10100 '
b10100 3
b1 2
#2000
b0 8
b1111 "
b1111 7
b10 /
b10 5
b111100001111 (
b111100001111 4
b11111111 '
b11111111 3
b10 2
#3000
b111111110000 "
b111111110000 7
b111111110000 <
b11 /
b11 5
b111100000000 (
b111100000000 4
b11110000 '
b11110000 3
b11 2
#4000
1$
b1111111111111111 "
b1111111111111111 7
1:
b1111111111111111 <
b100 /
b100 5
b101010101010101 (
b101010101010101 4
b1010101010101010 '
b1010101010101010 3
b100 2
#5000
1$
b1111111100000000 "
b1111111100000000 7
b1111111100000000 <
b101 /
b101 5
b11111111 '
b11111111 3
b101 2
#6000
0$
b110 "
b110 7
0:
b110 <
b110 /
b110 5
b11 '
b11 3
b110 2
#7000
b100 "
b100 7
b100 <
b111 /
b111 5
b1000 '
b1000 3
b111 2
#8000
b110010 "
b110010 7
b110010 <
b1000 /
b1000 5
b101 (
b101 4
b1010 '
b1010 3
b1000 2
#9000
b1100100 "
b1100100 7
b1100100 <
b1001 /
b1001 5
b1100011 '
b1100011 3
b1001 2
#10000
b1100011 "
b1100011 7
b1100011 <
b1010 /
b1010 5
b1100100 '
b1100100 3
b1010 2
#11000
b1001000110100 "
b1001000110100 7
b1001000110100 <
b1011 /
b1011 5
b1001000110100 '
b1001000110100 3
b1011 2
#12000
b101011001111000 "
b101011001111000 7
b101011001111000 <
b1100 /
b1100 5
b101011001111000 (
b101011001111000 4
b1100 2
#13000
1$
b1111000011110000 "
b1111000011110000 7
1:
b1111000011110000 <
b1101 /
b1101 5
b111100001111 (
b111100001111 4
b1111111111111111 '
b1111111111111111 3
b1101 2
#14000
1$
b1111111111111111 "
b1111111111111111 7
b1111111111111111 <
b1110 /
b1110 5
b0 (
b0 4
b0 '
b0 3
b1110 2
#15000
1!
0$
b0 "
b0 7
0:
1=
b0 <
b1111 /
b1111 5
b101010101010101 (
b101010101010101 4
b1010101010101010 '
b1010101010101010 3
b1111 2
#16000
1!
b0 /
b0 5
b0 (
b0 4
b0 '
b0 3
b10000 2
#17000
1%
b10000000000000000 8
1!
19
b1 (
b1 4
b1111111111111111 '
b1111111111111111 3
b10001 2
#18000
1#
1$
b1000000000000000 "
b1000000000000000 7
b1000000000000000 8
0!
0%
1:
1;
0=
09
b1000000000000000 <
b111111111111111 '
b111111111111111 3
b10010 2
#19000
1!
1%
b10000000000000000 8
0$
1#
b0 "
b0 7
0:
1=
19
b0 <
b1000000000000000 (
b1000000000000000 4
b1000000000000000 '
b1000000000000000 3
b10011 2
#20000
b0 8
0#
1!
0%
0;
09
b1 /
b1 5
b1100100 (
b1100100 4
b1100100 '
b1100100 3
b10100 2
#21000
1$
1%
b1111111111111011 "
b1111111111111011 7
b11111111111111011 8
0!
1:
0=
19
b1111111111111011 <
b1010 (
b1010 4
b101 '
b101 3
b10101 2
#22000
1#
b111111111111111 8
0$
0%
b111111111111111 "
b111111111111111 7
0:
1;
09
b111111111111111 <
b1 (
b1 4
b1000000000000000 '
b1000000000000000 3
b10110 2
#23000
1$
b0 8
0#
b1111111111111111 "
b1111111111111111 7
1:
0;
b1111111111111111 <
b10 /
b10 5
b1111111111111111 (
b1111111111111111 4
b1111111111111111 '
b1111111111111111 3
b10111 2
#24000
1!
0$
b0 "
b0 7
0:
1=
b0 <
b0 '
b0 3
b11000 2
#25000
1!
b11 /
b11 5
b0 (
b0 4
b11001 2
#26000
1!
b100 /
b100 5
b1010101010101010 (
b1010101010101010 4
b1010101010101010 '
b1010101010101010 3
b11010 2
#27000
1$
b1111111111111111 "
b1111111111111111 7
0!
1:
0=
b1111111111111111 <
b101 /
b101 5
b0 '
b0 3
b11011 2
#28000
1!
0$
b0 "
b0 7
0:
1=
b0 <
b110 /
b110 5
b1000000000000000 '
b1000000000000000 3
b11100 2
#29000
1!
b111 /
b111 5
b1 '
b1 3
b11101 2
#30000
1!
b1000 /
b1000 5
b0 (
b0 4
b111110100 '
b111110100 3
b11110 2
#31000
b10011010010 "
b10011010010 7
0!
0=
b10011010010 <
b1 (
b1 4
b10011010010 '
b10011010010 3
b11111 2
#32000
1!
b0 "
b0 7
1=
b0 <
b1001 /
b1001 5
b1111111111111111 '
b1111111111111111 3
b100000 2
#33000
1$
b1000000000000000 "
b1000000000000000 7
0!
1:
0=
b1000000000000000 <
b111111111111111 '
b111111111111111 3
b100001 2
#34000
1$
b1111111111111111 "
b1111111111111111 7
b1111111111111111 <
b1010 /
b1010 5
b0 '
b0 3
b100010 2
#35000
1$
b1010101111001101 "
b1010101111001101 7
b1010101111001101 <
b1011 /
b1011 5
b1010101111001101 '
b1010101111001101 3
b100011 2
#36000
0$
b1001000110100 "
b1001000110100 7
0:
b1001000110100 <
b1100 /
b1100 5
b1001000110100 (
b1001000110100 4
b100100 2
#37000
1!
b0 "
b0 7
1=
b0 <
b1101 /
b1101 5
b1111111111111111 (
b1111111111111111 4
b1111111111111111 '
b1111111111111111 3
b100101 2
#38000
1$
b1111111111111111 "
b1111111111111111 7
0!
1:
0=
b1111111111111111 <
b1110 /
b1110 5
b0 (
b0 4
b0 '
b0 3
b100110 2
#39000
1$
b1111111111111111 "
b1111111111111111 7
b1111 /
b1111 5
b1010101010101010 (
b1010101010101010 4
b1010101010101010 '
b1010101010101010 3
b100111 2
#40000
0$
b11010100100101 "
b11010100100101 7
0:
b11010100100101 <
0*
0.
0+
0)
b11010100100101 ,
b1001 /
b1001 5
b101111010000001 (
b101111010000001 4
b11010100100100 '
b11010100100100 3
b0 1
b101000 2
#41000
1$
b1010110111111110 "
b1010110111111110 7
1:
b1010110111111110 <
1*
b1010110111111110 ,
b1101 /
b1101 5
b111101100001101 (
b111101100001101 4
b101011001100011 '
b101011001100011 3
b1 1
b101001 2
#42000
1#
b11001001010011 8
0$
b11001001010011 "
b11001001010011 7
0:
1;
b11001001010011 <
0*
1+
b11001001010011 ,
b11001001010011 -
b1 /
b1 5
b101001000010010 (
b101001000010010 4
b1000010001100101 '
b1000010001100101 3
b10 1
b101010 2
#43000
b0 8
0#
b11111011111011 "
b11111011111011 7
0;
b11111011111011 <
0+
b11111011111011 ,
b1101 /
b1101 5
b1111000101110110 (
b1111000101110110 4
b1100110100001101 '
b1100110100001101 3
b11 1
b101011 2
#44000
b101011111101110 "
b101011111101110 7
b101011111101110 <
b101011111101110 ,
b1001 /
b1001 5
b1111011110001100 (
b1111011110001100 4
b101011111101101 '
b101011111101101 3
b100 1
b101100 2
#45000
b10010011000101 "
b10010011000101 7
b10010011000101 <
b10010011000101 ,
b1010 /
b1010 5
b1000010011000101 (
b1000010011000101 4
b10010011000110 '
b10010011000110 3
b101 1
b101101 2
#46000
b111001001100101 "
b111001001100101 7
b111001001100101 <
b111001001100101 ,
b10 /
b10 5
b111001001110111 (
b111001001110111 4
b1111011111100101 '
b1111011111100101 3
b110 1
b101110 2
#47000
b10000000000 "
b10000000000 7
b10000000000 <
b10000000000 ,
b1110 /
b1110 5
b110100111110010 (
b110100111110010 4
b1101101110001111 '
b1101101110001111 3
b111 1
b101111 2
#48000
b100111011000101 "
b100111011000101 7
b100111011000101 <
b100111011000101 ,
b1100 /
b1100 5
b100111011000101 (
b100111011000101 4
b111101011101000 '
b111101011101000 3
b1000 1
b110000 2
#49000
1$
b1101011101000010 "
b1101011101000010 7
1:
b1101011101000010 <
1*
b1101011101000010 ,
b101 /
b101 5
b101100000101101 (
b101100000101101 4
b10100010111101 '
b10100010111101 3
b1001 1
b110001 2
#50000
b1110100101101101 8
1$
b1110100101101101 "
b1110100101101101 7
b1110100101101101 <
b1110100101101101 ,
b1110100101101101 -
b0 /
b0 5
b1000011100001010 (
b1000011100001010 4
b110001001100011 '
b110001001100011 3
b1010 1
b110010 2
#51000
b0 8
1$
b1111111011011111 "
b1111111011011111 7
b1111111011011111 <
b1111111011011111 ,
b1101 /
b1101 5
b100010110101010 (
b100010110101010 4
b10000100100000 '
b10000100100000 3
b1011 1
b110011 2
#52000
1$
b1100011111101101 "
b1100011111101101 7
b1100011111101101 <
b1100011111101101 ,
b1011100000010011 (
b1011100000010011 4
b11111010010110 '
b11111010010110 3
b1100 1
b110100 2
#53000
0$
b10100110101100 "
b10100110101100 7
0:
b10100110101100 <
0*
b10100110101100 ,
b101 /
b101 5
b1101110101101011 (
b1101110101101011 4
b1101011001010011 '
b1101011001010011 3
b1101 1
b110101 2
#54000
1$
b1111010111111101 "
b1111010111111101 7
1:
b1111010111111101 <
1*
b1111010111111101 ,
b1101 /
b1101 5
b11111010101110 (
b11111010101110 4
b100101000000010 '
b100101000000010 3
b1110 1
b110110 2
#55000
0$
b111001011001110 "
b111001011001110 7
0:
b111001011001110 <
0*
b111001011001110 ,
b1010 /
b1010 5
b100100100100011 (
b100100100100011 4
b111001011001111 '
b111001011001111 3
b1111 1
b110111 2
#56000
b100000001000 "
b100000001000 7
b100000001000 <
b100000001000 ,
b10 /
b10 5
b100110000111100 (
b100110000111100 4
b101011001010 '
b101011001010 3
b10000 1
b111000 2
#57000
b100001000001010 "
b100001000001010 7
b100001000001010 <
b100001000001010 ,
b1000 /
b1000 5
b1011001101000001 (
b1011001101000001 4
b110000110001010 '
b110000110001010 3
b10001 1
b111001 2
#58000
1$
b1111001101111000 "
b1111001101111000 7
1:
b1111001101111000 <
1*
b1111001101111000 ,
b1011 /
b1011 5
b1001010001001 (
b1001010001001 4
b1111001101111000 '
b1111001101111000 3
b10010 1
b111010 2
#59000
0$
b1000001001 "
b1000001001 7
0:
b1000001001 <
0*
b1000001001 ,
b1110 /
b1110 5
b1111100111000110 (
b1111100111000110 4
b110010110110110 '
b110010110110110 3
b10011 1
b111011 2
#60000
b1010111100 "
b1010111100 7
b1010111100 <
b1010111100 ,
b1011 /
b1011 5
b1101110100101010 (
b1101110100101010 4
b1010111100 '
b1010111100 3
b10100 1
b111100 2
#61000
b1011 "
b1011 7
b1011 <
b1011 ,
b1111 /
b1111 5
b100000110000101 (
b100000110000101 4
b1011111001110001 '
b1011111001110001 3
b10101 1
b111101 2
#62000
1$
b1000110011000100 "
b1000110011000100 7
1:
b1000110011000100 <
1*
b1000110011000100 ,
b1110 /
b1110 5
b11001100111010 (
b11001100111010 4
b110000000111011 '
b110000000111011 3
b10110 1
b111110 2
#63000
0$
b100101100010110 "
b100101100010110 7
0:
b100101100010110 <
0*
b100101100010110 ,
b1001 /
b1001 5
b1001101111110001 (
b1001101111110001 4
b100101100010101 '
b100101100010101 3
b10111 1
b111111 2
#64000
b1111010001 "
b1111010001 7
b1111010001 <
b1111010001 ,
b1111 /
b1111 5
b1111101101001100 (
b1111101101001100 4
b11101100010 '
b11101100010 3
b11000 1
b1000000 2
#65000
b101000011000111 "
b101000011000111 7
b101000011000111 <
b101000011000111 ,
b111 /
b111 5
b1010100111111000 (
b1010100111111000 4
b1010000110001111 '
b1010000110001111 3
b11001 1
b1000001 2
#66000
b101011010011111 "
b101011010011111 7
b101011010011111 <
b101011010011111 ,
b1011 /
b1011 5
b1001010001011100 (
b1001010001011100 4
b101011010011111 '
b101011010011111 3
b11010 1
b1000010 2
#67000
b110100111010010 8
b110100111010010 "
b110100111010010 7
b110100111010010 <
b110100111010010 ,
b110100111010010 -
b0 /
b0 5
b11001001001001 (
b11001001001001 4
b11011110001001 '
b11011110001001 3
b11011 1
b1000011 2
#68000
1$
b0 8
b1000000110101110 "
b1000000110101110 7
1:
b1000000110101110 <
1*
b1000000110101110 ,
b110 /
b110 5
b1111110001010001 (
b1111110001010001 4
b1100000011010111 '
b1100000011010111 3
b11100 1
b1000100 2
#69000
1$
b1110111100011000 "
b1110111100011000 7
b1110111100011000 <
b1110111100011000 ,
b1000 /
b1000 5
b1100111011000010 (
b1100111011000010 4
b111111100001100 '
b111111100001100 3
b11101 1
b1000101 2
#70000
0$
b100100000110101 "
b100100000110101 7
0:
b100100000110101 <
0*
b100100000110101 ,
b10 /
b10 5
b1110110100111101 (
b1110110100111101 4
b101101001110111 '
b101101001110111 3
b11110 1
b1000110 2
#71000
b1111111 "
b1111111 7
b1111111 <
b1111111 ,
b1001 /
b1001 5
b1000000101101101 (
b1000000101101101 4
b1111110 '
b1111110 3
b11111 1
b1000111 2
#72000
b111000011100000 "
b111000011100000 7
b111000011100000 <
b111000011100000 ,
b101 /
b101 5
b1111011011010011 (
b1111011011010011 4
b1000111100011111 '
b1000111100011111 3
b100000 1
b1001000 2
#73000
1$
b1000100001111001 "
b1000100001111001 7
1:
b1000100001111001 <
1*
b1000100001111001 ,
b1001 /
b1001 5
b101100101011011 (
b101100101011011 4
b1000100001111000 '
b1000100001111000 3
b100001 1
b1001001 2
#74000
1$
b1010011101010110 "
b1010011101010110 7
b1010011101010110 <
b1010011101010110 ,
b1000 /
b1000 5
b1010111100101010 (
b1010111100101010 4
b1010111000111111 '
b1010111000111111 3
b100010 1
b1001010 2
#75000
0$
b110010001110 "
b110010001110 7
0:
b110010001110 <
0*
b110010001110 ,
b1100 /
b1100 5
b110010001110 (
b110010001110 4
b11100010000110 '
b11100010000110 3
b100011 1
b1001011 2
#76000
1$
b1011110111111110 "
b1011110111111110 7
1:
b1011110111111110 <
1*
b1011110111111110 ,
b11 /
b11 5
b1011110000100110 (
b1011110000100110 4
b1001100111111010 '
b1001100111111010 3
b100100 1
b1001100 2
#77000
1$
b1011110010101111 "
b1011110010101111 7
b1011110010101111 <
b1011110010101111 ,
b1010100000101111 (
b1010100000101111 4
b1011010010100011 '
b1011010010100011 3
b100101 1
b1001101 2
#78000
0$
b10101100101111 "
b10101100101111 7
0:
b10101100101111 <
0*
b10101100101111 ,
b111 /
b111 5
b110101000100 (
b110101000100 4
b101011001011111 '
b101011001011111 3
b100110 1
b1001110 2
#79000
b11011011001010 "
b11011011001010 7
b11011011001010 <
b11011011001010 ,
b1010 /
b1010 5
b1101011100110 (
b1101011100110 4
b11011011001011 '
b11011011001011 3
b100111 1
b1001111 2
#80000
1$
b1100000100101000 "
b1100000100101000 7
1:
b1100000100101000 <
1*
b1100000100101000 ,
b1110001011101101 (
b1110001011101101 4
b1100000100101001 '
b1100000100101001 3
b101000 1
b1010000 2
#81000
1$
b1010101100101111 "
b1010101100101111 7
b1010101100101111 <
b1010101100101111 ,
b1111 /
b1111 5
b1110001010110101 (
b1110001010110101 4
b1011011001100101 '
b1011011001100101 3
b101001 1
b1010001 2
#82000
1%
b10001100010111101 8
0$
b1100010111101 "
b1100010111101 7
0:
19
b1100010111101 <
0*
1)
b1100010111101 ,
b10001100010111101 -
b0 /
b0 5
b1111111101000100 (
b1111111101000100 4
b1100101111001 '
b1100101111001 3
b101010 1
b1010010 2
#83000
b0 8
0%
b101000001010100 "
b101000001010100 7
09
b101000001010100 <
0)
b101000001010100 ,
b1110 /
b1110 5
b1010110110101011 (
b1010110110101011 4
b101100101010 '
b101100101010 3
b101011 1
b1010011 2
#84000
b101001101100111 "
b101001101100111 7
b101001101100111 <
b101001101100111 ,
b1101 /
b1101 5
b1011110010011010 (
b1011110010011010 4
b1010110111011100 '
b1010110111011100 3
b101100 1
b1010100 2
